commonmark-stubs/METADATA.toml
commonmark-stubs/__init__.pyi
commonmark-stubs/blocks.pyi
commonmark-stubs/cmark.pyi
commonmark-stubs/common.pyi
commonmark-stubs/dump.pyi
commonmark-stubs/entitytrans.pyi
commonmark-stubs/inlines.pyi
commonmark-stubs/main.pyi
commonmark-stubs/node.pyi
commonmark-stubs/normalize_reference.pyi
commonmark-stubs/py.typed
commonmark-stubs/render/__init__.pyi
commonmark-stubs/render/html.pyi
commonmark-stubs/render/renderer.pyi
commonmark-stubs/render/rst.pyi
types_commonmark-0.9.2.20250330.dist-info/licenses/LICENSE
types_commonmark-0.9.2.20250330.dist-info/METADATA
types_commonmark-0.9.2.20250330.dist-info/WHEEL
types_commonmark-0.9.2.20250330.dist-info/top_level.txt
types_commonmark-0.9.2.20250330.dist-info/RECORD
